{
  "fetched_at": "2026-05-16T15:59:10+00:00",
  "since_hours": 5,
  "count": 4,
  "by_source": {
    "craigslist": 4,
    "auctionninja": 0
  },
  "an_watch_list": [],
  "listings": [
    {
      "post_id": "7934699737",
      "url": "https://newyork.craigslist.org/wch/msg/d/yonkers-paititi-violin-with-case/7934699737.html",
      "title": "Paititi Violin with case",
      "asking_price": 100,
      "location": "Yonkers",
      "posted_at": "2026-05-16T10:34:10-0400",
      "body": "Up for sale is a nice violin barely used in great condition. The ad will be removed once sold, please don’t if it’s still available.",
      "search_key": "instruments",
      "category": "msa",
      "source": "craigslist"
    },
    {
      "post_id": "7934691844",
      "url": "https://newyork.craigslist.org/wch/msg/d/pleasantville-drum-set/7934691844.html",
      "title": "Drum set",
      "asking_price": 350,
      "location": "Pleasantville",
      "posted_at": "2026-05-16T09:54:40-0400",
      "body": "Jazz drums set for $350 or best offer. Needs to go soon.",
      "thumbnail_url": "https://images.craigslist.org/00H0H_2pAcIjsjhBM_0MM132_600x450.jpg",
      "search_key": "instruments",
      "category": "msa",
      "source": "craigslist"
    },
    {
      "post_id": "7934678040",
      "url": "https://newyork.craigslist.org/wch/msg/d/yonkers-new-gator-lp-hardshell-case/7934678040.html",
      "title": "New Gator LP Hardshell Case",
      "asking_price": 100,
      "location": "Yonkers",
      "posted_at": "2026-05-16T08:24:58-0400",
      "body": "New Gator LP Hardshell Case Purchased a week ago to transport a Les Paul from New Hampshire to NY. No shipping, checks, money orders, no CL nonsense.",
      "thumbnail_url": "https://images.craigslist.org/00Z0Z_7gEWoaRPM2j_0CI0t2_600x450.jpg",
      "search_key": "instruments",
      "category": "msa",
      "source": "craigslist"
    },
    {
      "post_id": "7934676399",
      "url": "https://newyork.craigslist.org/wch/msg/d/katonah-zt-lunchbox-guitar-amp/7934676399.html",
      "title": "ZT Lunchbox 2 guitar amp amplifier good",
      "asking_price": 285,
      "location": "Katonah",
      "posted_at": "2026-05-16T08:12:27-0400",
      "body": "Works great! IYKYK - very loud, very portable, can power a 4x12 no problem. For some reason this one says \"reverb\" on it - it is more like the ambience knob on others. It is not the new version with an actual reverb circuit.",
      "search_key": "instruments",
      "category": "msa",
      "source": "craigslist"
    }
  ]
}