{
  "fetched_at": "2026-06-16T13:15:54+00:00",
  "since_hours": 5,
  "count": 4,
  "by_source": {
    "craigslist": 4,
    "auctionninja": 0
  },
  "an_watch_list": [],
  "listings": [
    {
      "post_id": "7941275912",
      "url": "https://newyork.craigslist.org/wch/clt/d/yonkers-new-vasa-museet-gustav-adolfs/7941275912.html",
      "title": "NEW Vasa Museet Gustav Adolf's Army Naval Gun crew 30 mm Metal Figures",
      "asking_price": 20,
      "location": "Yonkers",
      "posted_at": "2026-06-16T07:22:37-0400",
      "body": "NEW Vasa Museet Gustav Adolf’s Army 30 Years War 1618-1648 Vasa Naval Gun with Crew 30 mm Metal Figures",
      "thumbnail_url": "https://images.craigslist.org/00I0I_fqBiWOErL8r_0t20CI_600x450.jpg",
      "search_key": "collectibles",
      "category": "cba",
      "source": "craigslist"
    },
    {
      "post_id": "7941275850",
      "url": "https://newyork.craigslist.org/wch/clt/d/yonkers-chongqing-stilwell-museum-cbi/7941275850.html",
      "title": "Chongqing Stilwell Museum CBI Theater Patch and Stilwell Badge Set NEW",
      "asking_price": 25,
      "location": "westchester",
      "posted_at": "2026-06-16T07:21:56-0400",
      "body": "Chongqing Stilwell Museum CBI Theater Patch and Stilwell Badge Set NEW IN BOX Badge Gen. Joseph W. Stilwell 1883-1945",
      "thumbnail_url": "https://images.craigslist.org/00S0S_89qa83BdUaA_0CI0t2_600x450.jpg",
      "search_key": "collectibles",
      "category": "cba",
      "source": "craigslist"
    },
    {
      "post_id": "7941281137",
      "url": "https://newyork.craigslist.org/wch/tag/d/yonkers-step2-tropical-rainforest-water/7941281137.html",
      "title": "Step2 Tropical Rainforest Water Table        Table Only, no accessorie",
      "asking_price": 25,
      "location": "westchester",
      "posted_at": "2026-06-16T08:17:30-0400",
      "body": "Step2 Tropical Rainforest Water Table        Table Only, no accessories. Used outside will need a wipe down.",
      "thumbnail_url": "https://images.craigslist.org/00H0H_LWwAxRzl9n_0CI0t2_600x450.jpg",
      "search_key": "toys_games",
      "category": "taa",
      "source": "craigslist"
    },
    {
      "post_id": "7941280945",
      "url": "https://newyork.craigslist.org/wch/tag/d/yonkers-step2-up-down-roller-coaster/7941280945.html",
      "title": "Step2 Up & Down Roller Coaster Red Ride On Car      CAR ONLY",
      "asking_price": 20,
      "location": "westchester",
      "posted_at": "2026-06-16T08:15:54-0400",
      "body": "Step2 Up & Down Roller Coaster Red Ride On Car CAR ONLY",
      "thumbnail_url": "https://images.craigslist.org/00a0a_daT4CumMKNA_0CI0t2_600x450.jpg",
      "search_key": "toys_games",
      "category": "taa",
      "source": "craigslist"
    }
  ]
}